fignature/__about__.py
fignature/__init__.py
fignature-0.0.0.dist-info/METADATA
fignature-0.0.0.dist-info/WHEEL
fignature-0.0.0.dist-info/licenses/LICENSE.txt
fignature-0.0.0.dist-info/RECORD
