Metadata-Version: 2.1
Name: fignature
Version: 0.0.0
Summary: Fast implementation of inspect.signature()
Project-URL: Documentation, https://github.com/Bobronium/fignature#readme
Project-URL: Issues, https://github.com/Bobronium/fignature/issues
Project-URL: Source, https://github.com/Bobronium/fignature
Author-email: Bobronium <appkiller16@gmail.com>
License-Expression: MIT
License-File: LICENSE.txt
Classifier: Development Status :: 4 - Beta
Classifier: Programming Language :: Python
Classifier: Programming Language :: Python :: 3.7
Classifier: Programming Language :: Python :: 3.8
Classifier: Programming Language :: Python :: 3.9
Classifier: Programming Language :: Python :: 3.10
Classifier: Programming Language :: Python :: 3.11
Classifier: Programming Language :: Python :: Implementation :: CPython
Classifier: Programming Language :: Python :: Implementation :: PyPy
Requires-Python: >=3.7
